{
  "schema_version": "seasonal-classification/v1",
  "species": "Brimstone Butterfly",
  "model_family": "seasonal_presence",
  "classification": {
    "primary_class": "extended_spring_seasonal_presence",
    "timing": "spring",
    "season_width": "very_broad",
    "window_shape": "moderate",
    "post_peak_decline": "strong",
    "offseason_suppression": "strong",
    "peak_alignment": "early",
    "traits": [
      "spring_peak",
      "very_broad_season",
      "moderate_seasonal_window",
      "strong_post_peak_decline",
      "strong_offseason_suppression",
      "early_peak_alignment"
    ],
    "confidence": "medium"
  },
  "derived_metrics": {
    "season_start_month": 2.295,
    "season_end_month": 9.265,
    "forcing_peak_month": 4.065,
    "season_width_months": 6.97,
    "season_midpoint_month": 5.78,
    "season_start_label": "February",
    "season_end_label": "September",
    "forcing_peak_label": "April"
  },
  "parameter_evidence": {
    "GROWTH": 3.144,
    "DECAY": 1.744,
    "OOS_DECAY": 4.923,
    "POST_PEAK_DECAY": 4.209,
    "POST_PEAK_SHARPNESS": 5.448,
    "SEASON_START": 2.295,
    "SEASON_END": 9.265,
    "SHARPNESS": 6.121,
    "FORCING_PEAK": 4.065
  },
  "fit": {
    "score": null
  },
  "warnings": [],
  "summary": "Brimstone Butterfly is classified as extended spring seasonal presence. The fitted seasonal window runs from about February to September, with a spring peak around April. The season is very_broad, with a moderate active window, strong post-peak decline, and strong off-season suppression."
}
